{"cameraMode":{"drawMode":0,"name":"Shaded","section":"Shading Mode"},"sceneLighting":true,"audioPlay":false,"sceneViewState":{"m_AlwaysRefresh":false,"showFog":true,"showSkybox":true,"showFlares":true,"showImageEffects":true,"showParticleSystems":true,"showVisualEffectGraphs":true,"m_FxEnabled":true},"in2DMode":false,"pivot":{"x":51.9713020324707,"y":-18.23040008544922,"z":-1.3638111352920533},"rotation":{"x":-0.15265195071697236,"y":-0.6114941239356995,"z":0.1217217743396759,"w":-0.7667925953865051},"size":49.093910217285159,"orthographic":false}